{
    "errorBlankField": "No puedo tener un campo en blanco.",
    "errorInvalidName": "El nombre debe tener 3-10 caracteres.",
    "errorPasswordRequirements": "La contraseña debe tener 8-16 caracteres y un número / símbolo.",
    "errorInvalidPassword": "Tu contraseña es muy débil.",
    "errorInvalidEmail": "Por favor introduzca una dirección de correo electrónico válida.",
    "errorWrongPassword": "El usuario no existe o la contraseña es incorrecta.",
    "errorUserNotFound": "El usuario no existe o la contraseña es incorrecta.",
    "errorUserDisabled": "El usuario ha sido deshabilitado.",
    "errorEmailAlreadyExists": "El correo electrónico ya está en uso en una cuenta diferente.",
    "errorInvalidCredential": "Por favor introduzca una dirección de correo electrónico válida.",
    "errorImage": "Error al obtener la imagen.",
    "errorShare": "Error al compartir.",
    "errorDefault": "Ocurrió un error indefinido.",
    "settingGroupAccount": "Cuenta",
    "settingGroupGeneral": "General",
    "settingGroupPrivacy": "Intimidad",
    "settingGroupHidden": "Oculto",
    "settingLocale": "Idioma",
    "settingNotifications": "Notificaciones",
    "settingIsDark": "Modo nocturno",
    "settingProfileURL": "URL del perfil",
    "settingResetPassword": "Restablecer la contraseña",
    "mediaSelectionTitle": "¿De dónde quieres una foto?",
    "mediaSelectionGallery": "Galería",
    "mediaSelectionCamera": "Cámara",
    "welcomeTitle": "A diario",
    "welcomeSubtitle": "¡Prepararse!",
    "welcomeAccountAlready": "¿Ya tienes una cuenta?",
    "welcomeAccountAlreadyLogin": "¡ACCESO!",
    "welcomeGetStarted": "EMPEZAR",
    "authSignIn": "ACCESO",
    "authSignUp": "INSCRIBIRSE",
    "authFormName": "Nombre",
    "authFormEmail": "Correo electrónico",
    "authFormPass": "Contraseña",
    "authForgotPassword": "¿Has olvidado tu contraseña?",
    "authSwitchSignInPrimary": "¿Ya tienes una cuenta?",
    "authSwitchSignUpPrimary": "¿No tienes una cuenta?",
    "authSwitchSignInSecondary": "¡ACCESO!",
    "authSwitchSignUpSecondary": "¡INSCRIBIRSE!",
    "forgotPasswordTitle": "¿Olvidaste tu contraseña?",
    "forgotPasswordSubtitle": "Ingrese su correo electrónico de usuario a continuación para\nReciba un mensaje de restablecimiento de contraseña.",
    "forgotPasswordValidatorEmailFormat": "El correo electrónico no puede estar vacío",
    "forgotPasswordFormEmail": "Correo electrónico",
    "forgotPasswordSend": "Enviar",
    "forgotPasswordResendPrimary": "No lo entendí?",
    "forgotPasswordResendSecondary": "¡Resolver!",
    "settingsTitle": "Ajustes",
    "settingsResetPasswordSent": "E-mail ha sido enviado",
    "settingsSignOut": "DESCONECTAR"
}